sphinxsearch/__init__.py
sphinxsearch/compat.py
sphinxsearch/fields.py
sphinxsearch/lookups.py
sphinxsearch/models.py
sphinxsearch/routers.py
sphinxsearch/sql.py
sphinxsearch/utils.py
sphinxsearch/backend/__init__.py
sphinxsearch/backend/sphinx/__init__.py
sphinxsearch/backend/sphinx/base.py
sphinxsearch/backend/sphinx/compiler.py
django_sphinxsearch-4.2.0.dist-info/LICENSE.txt
django_sphinxsearch-4.2.0.dist-info/METADATA
django_sphinxsearch-4.2.0.dist-info/WHEEL
django_sphinxsearch-4.2.0.dist-info/top_level.txt
django_sphinxsearch-4.2.0.dist-info/RECORD
