Metadata-Version: 2.1
Name: django-sphinxsearch
Version: 4.2.0
Summary: Sphinxsearch database backend for django>=2.0
Home-page: http://github.com/tumb1er/django_sphinxsearch
Author: tumbler
Author-email: zimbler@gmail.com
License: Beerware
Platform: UNKNOWN
